optparse_mooi.py
optparse_pretty-0.1.1.dist-info/RECORD
optparse_pretty-0.1.1.dist-info/WHEEL
optparse_pretty-0.1.1.dist-info/zip-safe
optparse_pretty-0.1.1.dist-info/top_level.txt
optparse_pretty-0.1.1.dist-info/DESCRIPTION.rst
optparse_pretty-0.1.1.dist-info/pydist.json
optparse_pretty-0.1.1.dist-info/METADATA
